dashai_test_text_classification_plugin/__init__.py
dashai_test_text_classification_plugin/bow_text_classification_model.py
dashai_test_text_classification_plugin/text_classification_model.py
dashai_test_text_classification_plugin/text_classification_task.py
dashai_test_text_classification_plugin-0.0.1.dist-info/METADATA
dashai_test_text_classification_plugin-0.0.1.dist-info/WHEEL
dashai_test_text_classification_plugin-0.0.1.dist-info/entry_points.txt
dashai_test_text_classification_plugin-0.0.1.dist-info/RECORD
